zerogpu/__init__.py
zerogpu-0.1.0.dist-info/METADATA
zerogpu-0.1.0.dist-info/WHEEL
zerogpu-0.1.0.dist-info/RECORD
